aea_ledger_ethereum/__init__.py
aea_ledger_ethereum/ethereum.py
aea_ledger_ethereum/py.typed
aea_ledger_ethereum/test_tools/__init__.py
aea_ledger_ethereum/test_tools/constants.py
aea_ledger_ethereum/test_tools/docker_images.py
aea_ledger_ethereum/test_tools/fixture_helpers.py
aea_ledger_ethereum/test_tools/data/ethereum_private_key.txt
aea_ledger_ethereum/test_tools/data/ethereum_private_key_two.txt
open_aea_ledger_ethereum-2.0.8.dist-info/licenses/LICENSE
open_aea_ledger_ethereum-2.0.8.dist-info/METADATA
open_aea_ledger_ethereum-2.0.8.dist-info/WHEEL
open_aea_ledger_ethereum-2.0.8.dist-info/entry_points.txt
open_aea_ledger_ethereum-2.0.8.dist-info/top_level.txt
open_aea_ledger_ethereum-2.0.8.dist-info/RECORD
